jsonschemaform/__init__.py
jsonschemaform/default_settings.py
jsonschemaform/admin/__init__.py
jsonschemaform/admin/widgets/__init__.py
jsonschemaform/admin/widgets/jsonschema_widget.py
jsonschemaform/static/js/jsoneditor.min.js
jsonschemaform/static/js/jsonschema-form.js
jsonschemaform/templates/jsonschema_widget.html
django_jsonschema_form-1.0.3.dist-info/LICENSE
django_jsonschema_form-1.0.3.dist-info/METADATA
django_jsonschema_form-1.0.3.dist-info/WHEEL
django_jsonschema_form-1.0.3.dist-info/top_level.txt
django_jsonschema_form-1.0.3.dist-info/RECORD
