Metadata-Version: 2.1
Name: django-jsonschema-form
Version: 1.0.3
Summary: Django admin widgets to render jsonschema as forms
Home-page: https://www.collabo.com.br/
Author: Collabo Software Ltda
Author-email: basask@collabo.com.br
License: MIT
Platform: UNKNOWN
Classifier: Development Status :: 4 - Beta
Classifier: Environment :: Web Environment
Classifier: Framework :: Django
Classifier: Intended Audience :: Developers
Classifier: License :: OSI Approved :: MIT License
Classifier: Operating System :: OS Independent
Classifier: Programming Language :: Python
Classifier: Programming Language :: Python :: 2
Classifier: Topic :: Software Development :: Libraries :: Python Modules
